comk_hik_sdk
