Metadata-Version: 1.2
Name: comk-hik-sdk
Version: 1.0.5
Summary: comk个人封装海康官方sdk。
Home-page: UNKNOWN
Author: comk
Author-email: 1943336161@qq.com
Maintainer: comk
Maintainer-email: 1943336161@qq.com
License: BSD License
Platform: all
Classifier: Development Status :: 4 - Beta
Classifier: Operating System :: OS Independent
Classifier: Intended Audience :: Developers
Classifier: License :: OSI Approved :: BSD License
Classifier: Programming Language :: Python
Classifier: Programming Language :: Python :: Implementation
Classifier: Programming Language :: Python :: 3.6
Classifier: Programming Language :: Python :: 3.7
Classifier: Topic :: Software Development :: Libraries
